MANIFEST.in
README.rst
setup.py
cerebro/__init__.py
cerebro/cerebro.py
cerebro/core/__init__.py
cerebro/core/factory.py
cerebro/data/__init__.py
cerebro/data/datasets/dataset.csv
cerebro/data/neurons/__init__.py
cerebro/data/neurons/datetime_util.py
cerebro/data/neurons/simple.py
cerebro/neuron/__init__.py
cerebro/neuron/config.py
cerebro/neuron/constants.py
cerebro/neuron/entities.py
cerebro/neuron/finder.py
cerebro/neuron/manager.py
cerebro/neuron/neuron.py
cerebro/nlp/__init__.py
cerebro/nlp/classifier.py
cerebro/nlp/constants.py
cerebro/nlp/nlp.py
cerebro/nlp/parser.py
cerebro/tests/__init__.py
cerebro/tests/core/__init__.py
cerebro/tests/core/test_factory.py
cerebro/tests/neuron/__init__.py
cerebro/tests/neuron/test_config.py
cerebro/tests/neuron/test_entities.py
cerebro/tests/neuron/test_finder.py
cerebro/tests/neuron/test_manager.py
cerebro/tests/neuron/test_neuron.py
cerebro/tests/nlp/__init__.py
cerebro/tests/nlp/test_classifier.py
cerebro/tests/nlp/test_nlp.py
cerebro/tests/nlp/test_parser.py
cerebro/tests/test_neurons/__init__.py
cerebro/tests/test_neurons/test_datetime.py
cerebro/tests/test_neurons/test_simple.py
lebot_cerebro.egg-info/PKG-INFO
lebot_cerebro.egg-info/SOURCES.txt
lebot_cerebro.egg-info/dependency_links.txt
lebot_cerebro.egg-info/not-zip-safe
lebot_cerebro.egg-info/requires.txt
lebot_cerebro.egg-info/top_level.txt