Metadata-Version: 1.1
Name: lebot-cerebro
Version: 0.1.0.dev8
Summary: Core engine for LeBot
Home-page: https://github.com/Le-Bot/cerebro
Author: LeBot
Author-email: sanket.upadhyay@infoud.co.in
License: MIT
Keywords: Chat Bot, AI
Platform: UNKNOWN
Classifier: Development Status :: 2 - Pre-Alpha
Classifier: License :: OSI Approved :: MIT License
Classifier: Programming Language :: Python :: 2.7
Classifier: Topic :: Scientific/Engineering :: Artificial Intelligence
